numeritos.py
numeritos-1.0.dist-info/METADATA
numeritos-1.0.dist-info/WHEEL
numeritos-1.0.dist-info/top_level.txt
numeritos-1.0.dist-info/RECORD
