Metadata-Version: 2.1
Name: numeritos
Version: 1.0
Summary: Librería para Data Scientists
Author-email: DS_The Bridge_Junio 22 <saradevv@gmail.com>
Project-URL: Homepage, https://github.com/Masara00/numeritos/tree/develop
Classifier: Programming Language :: Python :: 3
Classifier: License :: OSI Approved :: MIT License
Classifier: Operating System :: OS Independent
Classifier: Programming Language :: Python
Classifier: Programming Language :: Python :: 2.7
Classifier: Programming Language :: Python :: 3.3
Classifier: Programming Language :: Python :: 3.4
Classifier: Programming Language :: Python :: 3.5
Classifier: Programming Language :: Python :: 3.6
Classifier: Programming Language :: Python :: 3.7
Requires-Dist: pandas
Requires-Dist: numpy
Requires-Dist: matplotlib
Requires-Dist: seaborn
Requires-Dist: plotly
Requires-Dist: regex
Requires-Dist: joypy
Requires-Dist: wget
Requires-Dist: pygame
Requires-Dist: datetime
Requires-Dist: scikit-learn
Requires-Dist: imblearn
Requires-Dist: opencv-python
Requires-Dist: scikit-image
